<annotation>
	<folder>JPEGImages</folder>
	<filename>IMG0571.jpg</filename>
	<path>/home/edmond/data/caffe-data/JPEGImages/IMG0571.jpg</path>
	<source>
		<database>Unknown</database>
	</source>
	<size>
		<width>480</width>
		<height>720</height>
		<depth>3</depth>
	</size>
	<segmented>0</segmented>
	<object>
		<name>gear</name>
		<pose>Unspecified</pose>
		<truncated>0</truncated>
		<difficult>0</difficult>
		<bndbox>
			<xmin>149</xmin>
			<ymin>239</ymin>
			<xmax>192</xmax>
			<ymax>330</ymax>
		</bndbox>
	</object>
	<object>
		<name>gear</name>
		<pose>Unspecified</pose>
		<truncated>0</truncated>
		<difficult>0</difficult>
		<bndbox>
			<xmin>325</xmin>
			<ymin>251</ymin>
			<xmax>378</xmax>
			<ymax>342</ymax>
		</bndbox>
	</object>
</annotation>
